{
  "metadata": {
    "source": "Modèle corrigé — OSRM + coefficients de congestion Kinshasa",
    "basedOn": "travel-osrm.json (OSRM free-flow matrix)",
    "computedAt": "2026-02-23T12:42:17.984Z",
    "methodology": "Matrice A — Plafond de vitesse: les durées OSRM (vitesse moyenne ~49 km/h) sont recalculées avec un plafond de 40 km/h basé sur les vitesses réelles des axes bitumés (trunk/primary). Matrice B — Coefficients temporels: 5 profils horaires appliquent un coefficient réducteur sur la vitesse de base pour simuler les variations diurnes. Matrice C — Pénalités de nœuds (Grand Marché +25 min, Rond-Point Victoire +15 min, Rond-Point Ngaba +15 min, Marché de la Liberté +20 min, Kingasani +15 min): NON appliquées à ce niveau agrégé OD. Documentées pour application future en routage per-segment.",
    "units": {
      "durations": "minutes",
      "distances": "km"
    },
    "sources": [
      {
        "ref": "Banque Mondiale (2018)",
        "title": "Revue de l'urbanisation en République Démocratique du Congo",
        "contribution": "Validation de la vitesse moyenne intercommunale à 14 km/h"
      },
      {
        "ref": "JICA / PDTK (2019)",
        "title": "Plan Directeur des Transports Urbains de Kinshasa — Horizon 2030-2040",
        "contribution": "Vitesses en flux libre par type de voirie, débits maximaux (137 véh/h sur Blvd Lumumba)"
      },
      {
        "ref": "ESI Preprints (Décembre 2025)",
        "title": "Mobilité et circulation dans les villes d'Afrique Centrale — Mfewou A. et al.",
        "contribution": "Temps de trajet moyen par ménage: 1h45, impact du transport informel"
      }
    ],
    "nodePenalties": [
      {
        "zone": "Marché de la Liberté / Masina",
        "cause": "Minibus, vendeurs, piétons",
        "penalty": "15–20 min"
      },
      {
        "zone": "Rond-Point Victoire (Kalamu)",
        "cause": "Hub informel (Wewas, taxis)",
        "penalty": "12–15 min"
      },
      {
        "zone": "Rond-Point Ngaba",
        "cause": "Goulot d'étranglement Sud",
        "penalty": "15 min"
      },
      {
        "zone": "Grand Marché (Zando)",
        "cause": "Saturation commerciale diurne",
        "penalty": "25 min"
      },
      {
        "zone": "Kingasani (Pascal)",
        "cause": "Marché spontané sur la chaussée",
        "penalty": "10–15 min"
      }
    ]
  },
  "communes": [
    "Kintambo",
    "Bandalungwa",
    "Kasa-Vubu",
    "Lingwala",
    "Gombe",
    "Kinshasa",
    "Barumbu",
    "Kalamu",
    "Makala",
    "Bumbu",
    "Selembao",
    "Ngaba",
    "Limete",
    "Matete",
    "Kisenso",
    "Kimbanseke",
    "N'djili",
    "Nsele",
    "Masina",
    "Maluku",
    "Ngaliema",
    "Mont Ngafula",
    "Lemba",
    "Ngiri-Ngiri"
  ],
  "distances": [
    [
      0,
      1.1,
      4.9,
      6.1,
      8.9,
      6.9,
      8,
      6.1,
      8.6,
      6.5,
      8.3,
      9.8,
      12.3,
      14.5,
      19.2,
      21.4,
      18,
      37.5,
      21.5,
      163.5,
      7.4,
      28.8,
      16.2,
      4.4
    ],
    [
      1.1,
      0,
      4.1,
      5.3,
      8,
      6.1,
      7.2,
      5.3,
      7.8,
      5.7,
      7.5,
      9,
      11.5,
      13.7,
      18.4,
      20.6,
      17.2,
      36.7,
      20.7,
      162.7,
      8.4,
      28,
      15.4,
      3.6
    ],
    [
      4.9,
      4.1,
      0,
      2.7,
      5,
      3,
      4.2,
      2.3,
      8.1,
      3.8,
      8.4,
      7.5,
      8.4,
      10.6,
      15.3,
      17.5,
      14.1,
      33.6,
      17.7,
      159.6,
      12.3,
      28.9,
      12.4,
      2.4
    ],
    [
      5.6,
      4.7,
      2.8,
      0,
      3.4,
      1.9,
      3.1,
      4.3,
      10.6,
      7.2,
      9,
      10.1,
      8.5,
      11.3,
      16,
      18.2,
      14.9,
      34.4,
      18.4,
      160.3,
      10.6,
      29.5,
      13.1,
      5.1
    ],
    [
      8.8,
      7.9,
      5,
      3.3,
      0,
      2.1,
      2.4,
      5.1,
      10.8,
      10.4,
      12.2,
      10.3,
      7.8,
      11.5,
      16.2,
      18.4,
      15.1,
      34.5,
      18.6,
      160.5,
      12.6,
      32.7,
      13.3,
      6.9
    ],
    [
      6.8,
      5.9,
      3,
      1.7,
      2.1,
      0,
      1.8,
      3.1,
      8.9,
      8.4,
      10.3,
      8.3,
      6.7,
      9.5,
      14.2,
      16.4,
      13.1,
      32.6,
      16.6,
      158.5,
      12.1,
      30.8,
      11.3,
      4.9
    ],
    [
      8,
      7.2,
      4.3,
      2.9,
      2.4,
      1.6,
      0,
      4.3,
      10.1,
      9.6,
      11.5,
      9.5,
      5,
      10.8,
      15.5,
      17.6,
      14.3,
      33.8,
      17.8,
      159.8,
      13.3,
      32,
      12.5,
      6.1
    ],
    [
      6.1,
      5.3,
      2.3,
      4.7,
      5.1,
      3.1,
      3.5,
      0,
      6,
      5,
      9.6,
      5.5,
      7.1,
      7.5,
      12.2,
      14.4,
      11.1,
      30.6,
      14.6,
      156.5,
      13.5,
      28.6,
      9.3,
      3.7
    ],
    [
      8.7,
      7.8,
      8.1,
      10.4,
      10.3,
      8.8,
      9.1,
      6,
      0,
      2.1,
      4.9,
      1.9,
      12.7,
      6.6,
      8.9,
      15.5,
      12.1,
      31.6,
      15.6,
      157.6,
      15.9,
      24,
      3.8,
      4.3
    ],
    [
      6.5,
      5.7,
      3.8,
      7.7,
      10.4,
      8.4,
      9.6,
      5,
      2.1,
      0,
      4.9,
      3.8,
      13.9,
      8.9,
      11.2,
      15.3,
      12,
      31.5,
      15.5,
      157.5,
      13.9,
      25.4,
      6.1,
      2.4
    ],
    [
      8.4,
      7.6,
      8.3,
      9.5,
      12.3,
      10.3,
      11.5,
      9.6,
      4.9,
      4.9,
      0,
      7.1,
      15.7,
      10.3,
      12.6,
      19.2,
      15.9,
      35.4,
      19.4,
      161.3,
      11.3,
      20.7,
      7.5,
      6
    ],
    [
      9.8,
      8.9,
      7.6,
      9.9,
      9.7,
      8.3,
      8.6,
      5.5,
      1.9,
      3.8,
      7,
      0,
      12.2,
      5.2,
      7.5,
      13,
      9.6,
      29.1,
      13.1,
      155.1,
      17.1,
      24.5,
      3.9,
      5.6
    ],
    [
      12.1,
      11.2,
      8.3,
      8.3,
      7.7,
      6.7,
      4.9,
      7.4,
      12,
      13.7,
      15.6,
      11.4,
      0,
      12.6,
      17.3,
      19.5,
      16.1,
      35.6,
      19.6,
      161.6,
      19.5,
      35.5,
      14.3,
      10.2
    ],
    [
      14.5,
      13.6,
      10.7,
      11.1,
      11,
      9.5,
      9.8,
      7.5,
      6.5,
      8.8,
      10.4,
      5.2,
      12.6,
      0,
      4.5,
      9.4,
      6.1,
      25.5,
      9.6,
      151.5,
      21.9,
      23.1,
      4.5,
      12.6
    ],
    [
      19.2,
      18.3,
      15.4,
      15.8,
      15.7,
      14.2,
      14.5,
      12.2,
      8.8,
      11.1,
      12.7,
      7.5,
      17.3,
      4.9,
      0,
      13,
      9.6,
      29.1,
      13.2,
      155.1,
      26.5,
      21,
      6,
      17.3
    ],
    [
      21.3,
      20.4,
      17.5,
      17.9,
      17.8,
      16.3,
      16.6,
      14.3,
      16.6,
      15.5,
      24.8,
      13,
      19.4,
      9.5,
      13.1,
      0,
      3.6,
      24,
      8.9,
      149.9,
      28.7,
      21.7,
      14.6,
      19.4
    ],
    [
      17.9,
      17.1,
      14.2,
      14.6,
      14.4,
      13,
      13.3,
      11,
      13.2,
      12.2,
      21.4,
      9.7,
      16.1,
      6.2,
      9.7,
      3.6,
      0,
      23.5,
      7.5,
      149.5,
      25.3,
      22.3,
      11.2,
      16
    ],
    [
      43.2,
      42.4,
      39.5,
      39.9,
      39.7,
      38.3,
      38.6,
      36.3,
      38.5,
      37.4,
      46.7,
      34.9,
      41.3,
      31.4,
      35,
      29.8,
      29.3,
      0,
      28.8,
      141.1,
      50.6,
      51.9,
      36.5,
      41.3
    ],
    [
      21.4,
      20.6,
      17.7,
      18.1,
      17.9,
      16.5,
      16.8,
      14.5,
      16.7,
      15.6,
      24.9,
      13.1,
      19.5,
      9.6,
      13.2,
      8.9,
      7.5,
      23,
      0,
      148.9,
      28.8,
      30.1,
      14.7,
      19.5
    ],
    [
      163.4,
      162.6,
      159.7,
      160.1,
      159.9,
      158.5,
      158.8,
      156.5,
      158.7,
      157.6,
      166.9,
      155.1,
      161.5,
      151.6,
      155.2,
      150,
      149.5,
      149.9,
      149,
      0,
      170.8,
      172.1,
      156.7,
      161.5
    ],
    [
      7.5,
      8.4,
      12.3,
      10.6,
      12.5,
      12.1,
      13.3,
      13.5,
      16,
      13.8,
      11.4,
      17.2,
      19.7,
      21.8,
      26.6,
      28.7,
      25.4,
      44.9,
      28.9,
      170.9,
      0,
      26.2,
      23.6,
      11.7
    ],
    [
      29,
      28.2,
      29,
      30.2,
      32.9,
      30.9,
      32.1,
      28.7,
      24,
      25.5,
      20.9,
      24.7,
      36.4,
      23.1,
      21,
      21.7,
      22.3,
      46.1,
      30.1,
      172.1,
      26.3,
      0,
      25.1,
      26.6
    ],
    [
      17,
      16.1,
      13.2,
      13.6,
      13.5,
      12,
      12.3,
      7.8,
      3.8,
      6.1,
      7.6,
      3.9,
      15.1,
      4.5,
      6,
      13.4,
      10,
      29.5,
      13.5,
      155.5,
      24,
      25.2,
      0,
      7.9
    ],
    [
      4.4,
      3.6,
      2.4,
      4.6,
      6.9,
      4.9,
      6.1,
      3.7,
      4.3,
      2.3,
      6,
      5.5,
      10.4,
      12.5,
      17.3,
      19.4,
      16.1,
      35.6,
      19.6,
      161.6,
      11.8,
      26.5,
      7.9,
      0
    ]
  ],
  "defaultProfile": "diurne",
  "profiles": {
    "nuit": {
      "label": "Nuit (00h–05h)",
      "hours": "00h00 – 05h00",
      "coeff": 1,
      "speedRange": "30–40 km/h",
      "traffic": "Fluide",
      "durations": [
        [
          0,
          2,
          7,
          9,
          13,
          10,
          12,
          9,
          13,
          10,
          13,
          15,
          19,
          22,
          29,
          32,
          27,
          56,
          32,
          245,
          11,
          43,
          24,
          7
        ],
        [
          2,
          0,
          6,
          8,
          12,
          9,
          11,
          8,
          12,
          9,
          11,
          14,
          17,
          21,
          28,
          31,
          26,
          55,
          31,
          244,
          13,
          42,
          23,
          5
        ],
        [
          7,
          6,
          0,
          4,
          8,
          5,
          6,
          4,
          12,
          6,
          13,
          11,
          13,
          16,
          23,
          26,
          21,
          50,
          27,
          239,
          19,
          43,
          19,
          4
        ],
        [
          8,
          7,
          4,
          0,
          5,
          3,
          5,
          7,
          16,
          11,
          14,
          15,
          13,
          17,
          24,
          27,
          22,
          52,
          28,
          241,
          16,
          44,
          20,
          8
        ],
        [
          13,
          12,
          8,
          5,
          0,
          3,
          4,
          8,
          16,
          16,
          18,
          16,
          12,
          17,
          24,
          28,
          23,
          52,
          28,
          241,
          19,
          49,
          20,
          10
        ],
        [
          10,
          9,
          5,
          3,
          3,
          0,
          3,
          5,
          13,
          13,
          16,
          13,
          10,
          14,
          21,
          25,
          20,
          49,
          25,
          238,
          18,
          46,
          17,
          7
        ],
        [
          12,
          11,
          7,
          4,
          4,
          2,
          0,
          7,
          15,
          14,
          17,
          14,
          8,
          16,
          23,
          26,
          22,
          51,
          27,
          240,
          20,
          48,
          19,
          9
        ],
        [
          9,
          8,
          4,
          7,
          8,
          5,
          5,
          0,
          9,
          8,
          14,
          8,
          11,
          11,
          18,
          22,
          17,
          46,
          22,
          235,
          20,
          43,
          14,
          6
        ],
        [
          13,
          12,
          12,
          16,
          16,
          13,
          14,
          9,
          0,
          3,
          7,
          3,
          19,
          10,
          13,
          23,
          18,
          47,
          23,
          236,
          24,
          36,
          6,
          7
        ],
        [
          10,
          9,
          6,
          12,
          16,
          13,
          14,
          8,
          3,
          0,
          7,
          6,
          21,
          13,
          17,
          23,
          18,
          47,
          23,
          236,
          21,
          38,
          9,
          4
        ],
        [
          13,
          11,
          13,
          14,
          19,
          16,
          17,
          14,
          7,
          7,
          0,
          11,
          24,
          16,
          19,
          29,
          24,
          53,
          29,
          242,
          17,
          31,
          11,
          9
        ],
        [
          15,
          13,
          11,
          15,
          15,
          13,
          13,
          8,
          3,
          6,
          11,
          0,
          18,
          8,
          11,
          20,
          14,
          44,
          20,
          233,
          26,
          37,
          6,
          8
        ],
        [
          18,
          17,
          13,
          13,
          12,
          10,
          7,
          11,
          18,
          21,
          23,
          17,
          0,
          19,
          26,
          29,
          24,
          53,
          29,
          242,
          29,
          53,
          22,
          15
        ],
        [
          22,
          20,
          16,
          17,
          17,
          14,
          15,
          11,
          10,
          13,
          16,
          8,
          19,
          0,
          7,
          14,
          9,
          38,
          14,
          227,
          33,
          35,
          7,
          19
        ],
        [
          29,
          28,
          23,
          24,
          24,
          21,
          22,
          18,
          13,
          17,
          19,
          11,
          26,
          7,
          0,
          20,
          14,
          44,
          20,
          233,
          40,
          32,
          9,
          26
        ],
        [
          32,
          31,
          26,
          27,
          27,
          25,
          25,
          22,
          25,
          23,
          37,
          20,
          29,
          14,
          20,
          0,
          5,
          36,
          13,
          225,
          43,
          33,
          22,
          29
        ],
        [
          27,
          26,
          21,
          22,
          22,
          20,
          20,
          17,
          20,
          18,
          32,
          15,
          24,
          9,
          15,
          5,
          0,
          35,
          11,
          224,
          38,
          34,
          17,
          24
        ],
        [
          65,
          64,
          59,
          60,
          60,
          58,
          58,
          55,
          58,
          56,
          70,
          52,
          62,
          47,
          53,
          45,
          44,
          0,
          43,
          212,
          76,
          78,
          55,
          62
        ],
        [
          32,
          31,
          27,
          27,
          27,
          25,
          25,
          22,
          25,
          23,
          37,
          20,
          29,
          14,
          20,
          13,
          11,
          35,
          0,
          223,
          43,
          45,
          22,
          29
        ],
        [
          245,
          244,
          240,
          240,
          240,
          238,
          238,
          235,
          238,
          236,
          250,
          233,
          242,
          227,
          233,
          225,
          224,
          225,
          224,
          0,
          256,
          258,
          235,
          242
        ],
        [
          11,
          13,
          19,
          16,
          19,
          18,
          20,
          20,
          24,
          21,
          17,
          26,
          30,
          33,
          40,
          43,
          38,
          67,
          43,
          256,
          0,
          39,
          35,
          18
        ],
        [
          44,
          42,
          44,
          45,
          49,
          46,
          48,
          43,
          36,
          38,
          31,
          37,
          55,
          35,
          32,
          33,
          34,
          69,
          45,
          258,
          40,
          0,
          38,
          40
        ],
        [
          26,
          24,
          20,
          20,
          20,
          18,
          19,
          12,
          6,
          9,
          11,
          6,
          23,
          7,
          9,
          20,
          15,
          44,
          20,
          233,
          36,
          38,
          0,
          12
        ],
        [
          7,
          5,
          4,
          7,
          10,
          7,
          9,
          6,
          7,
          4,
          9,
          8,
          16,
          19,
          26,
          29,
          24,
          53,
          29,
          242,
          18,
          40,
          12,
          0
        ]
      ]
    },
    "pointe_matin": {
      "label": "Hyper-pointe matin (07h–09h)",
      "hours": "07h00 – 09h00",
      "coeff": 0.25,
      "speedRange": "8–10 km/h",
      "traffic": "Hyper-congestion",
      "durations": [
        [
          0,
          7,
          30,
          37,
          54,
          42,
          48,
          37,
          52,
          39,
          50,
          59,
          74,
          87,
          115,
          128,
          108,
          225,
          129,
          981,
          44,
          173,
          97,
          26
        ],
        [
          7,
          0,
          24,
          32,
          48,
          37,
          43,
          32,
          47,
          34,
          45,
          54,
          69,
          82,
          110,
          124,
          103,
          220,
          124,
          976,
          50,
          168,
          92,
          22
        ],
        [
          30,
          24,
          0,
          16,
          30,
          18,
          25,
          14,
          49,
          23,
          50,
          45,
          50,
          64,
          92,
          105,
          85,
          202,
          106,
          958,
          74,
          174,
          74,
          14
        ],
        [
          34,
          28,
          17,
          0,
          20,
          12,
          19,
          26,
          64,
          43,
          54,
          61,
          51,
          68,
          96,
          109,
          90,
          206,
          110,
          962,
          64,
          177,
          79,
          31
        ],
        [
          53,
          48,
          30,
          20,
          0,
          13,
          14,
          31,
          65,
          62,
          73,
          62,
          47,
          69,
          97,
          110,
          91,
          207,
          112,
          963,
          76,
          196,
          80,
          42
        ],
        [
          41,
          36,
          18,
          10,
          13,
          0,
          11,
          19,
          54,
          50,
          62,
          50,
          40,
          57,
          85,
          98,
          79,
          196,
          100,
          951,
          73,
          185,
          68,
          30
        ],
        [
          48,
          43,
          26,
          18,
          14,
          10,
          0,
          26,
          61,
          58,
          69,
          57,
          30,
          65,
          93,
          106,
          86,
          203,
          107,
          959,
          80,
          192,
          75,
          37
        ],
        [
          37,
          32,
          14,
          28,
          31,
          19,
          21,
          0,
          36,
          30,
          58,
          33,
          43,
          45,
          73,
          86,
          67,
          184,
          88,
          939,
          81,
          172,
          56,
          22
        ],
        [
          52,
          47,
          49,
          62,
          62,
          53,
          55,
          36,
          0,
          13,
          30,
          12,
          76,
          40,
          54,
          93,
          73,
          190,
          94,
          946,
          96,
          144,
          23,
          26
        ],
        [
          39,
          34,
          23,
          46,
          62,
          50,
          58,
          30,
          13,
          0,
          30,
          23,
          84,
          54,
          67,
          92,
          72,
          189,
          93,
          945,
          84,
          152,
          37,
          14
        ],
        [
          50,
          46,
          50,
          57,
          74,
          62,
          69,
          58,
          30,
          30,
          0,
          43,
          94,
          62,
          76,
          115,
          96,
          212,
          116,
          968,
          68,
          124,
          45,
          36
        ],
        [
          59,
          54,
          46,
          60,
          58,
          50,
          52,
          33,
          12,
          23,
          42,
          0,
          73,
          31,
          45,
          78,
          58,
          175,
          79,
          931,
          103,
          147,
          24,
          34
        ],
        [
          73,
          67,
          50,
          50,
          46,
          40,
          30,
          44,
          72,
          82,
          94,
          68,
          0,
          76,
          104,
          117,
          97,
          214,
          118,
          970,
          117,
          213,
          86,
          61
        ],
        [
          87,
          82,
          64,
          67,
          66,
          57,
          59,
          45,
          39,
          53,
          62,
          31,
          76,
          0,
          27,
          56,
          37,
          153,
          58,
          909,
          132,
          139,
          27,
          76
        ],
        [
          115,
          110,
          92,
          95,
          94,
          85,
          87,
          73,
          53,
          67,
          76,
          45,
          104,
          30,
          0,
          78,
          58,
          175,
          79,
          931,
          159,
          126,
          36,
          104
        ],
        [
          128,
          122,
          105,
          108,
          107,
          98,
          100,
          86,
          100,
          93,
          149,
          78,
          116,
          57,
          79,
          0,
          22,
          144,
          54,
          900,
          172,
          130,
          88,
          116
        ],
        [
          108,
          103,
          85,
          88,
          86,
          78,
          80,
          66,
          79,
          73,
          128,
          58,
          97,
          37,
          58,
          22,
          0,
          141,
          45,
          897,
          152,
          134,
          67,
          96
        ],
        [
          259,
          254,
          237,
          240,
          238,
          230,
          232,
          218,
          231,
          224,
          280,
          210,
          248,
          188,
          210,
          179,
          176,
          0,
          173,
          847,
          304,
          312,
          219,
          248
        ],
        [
          128,
          124,
          106,
          109,
          108,
          99,
          101,
          87,
          100,
          94,
          150,
          79,
          117,
          58,
          79,
          54,
          45,
          138,
          0,
          894,
          173,
          181,
          88,
          117
        ],
        [
          980,
          976,
          958,
          961,
          960,
          951,
          953,
          939,
          952,
          946,
          1002,
          931,
          969,
          910,
          931,
          900,
          897,
          900,
          894,
          0,
          1025,
          1033,
          940,
          969
        ],
        [
          45,
          50,
          74,
          64,
          75,
          73,
          80,
          81,
          96,
          83,
          68,
          103,
          118,
          131,
          160,
          172,
          152,
          270,
          174,
          1026,
          0,
          157,
          142,
          70
        ],
        [
          174,
          169,
          174,
          181,
          198,
          186,
          193,
          172,
          144,
          153,
          126,
          148,
          218,
          139,
          126,
          130,
          134,
          277,
          181,
          1033,
          158,
          0,
          151,
          160
        ],
        [
          102,
          97,
          79,
          82,
          81,
          72,
          74,
          47,
          23,
          37,
          46,
          24,
          91,
          27,
          36,
          80,
          60,
          177,
          81,
          933,
          144,
          151,
          0,
          48
        ],
        [
          26,
          22,
          14,
          28,
          42,
          30,
          37,
          22,
          26,
          14,
          36,
          33,
          62,
          75,
          104,
          116,
          97,
          214,
          118,
          970,
          71,
          159,
          48,
          0
        ]
      ]
    },
    "diurne": {
      "label": "Journée (09h–16h)",
      "hours": "09h00 – 16h00",
      "coeff": 0.35,
      "speedRange": "12–14 km/h",
      "traffic": "Activité",
      "durations": [
        [
          0,
          5,
          21,
          26,
          38,
          30,
          34,
          26,
          37,
          28,
          36,
          42,
          53,
          62,
          82,
          92,
          77,
          161,
          92,
          701,
          32,
          123,
          69,
          19
        ],
        [
          5,
          0,
          17,
          23,
          34,
          26,
          31,
          23,
          33,
          25,
          32,
          39,
          49,
          59,
          79,
          88,
          74,
          157,
          89,
          697,
          36,
          120,
          66,
          15
        ],
        [
          21,
          17,
          0,
          12,
          21,
          13,
          18,
          10,
          35,
          16,
          36,
          32,
          36,
          45,
          66,
          75,
          61,
          144,
          76,
          684,
          53,
          124,
          53,
          10
        ],
        [
          24,
          20,
          12,
          0,
          15,
          8,
          13,
          19,
          45,
          31,
          39,
          43,
          37,
          49,
          69,
          78,
          64,
          147,
          79,
          687,
          45,
          127,
          56,
          22
        ],
        [
          38,
          34,
          21,
          14,
          0,
          9,
          10,
          22,
          46,
          45,
          52,
          44,
          33,
          49,
          69,
          79,
          65,
          148,
          80,
          688,
          54,
          140,
          57,
          30
        ],
        [
          29,
          25,
          13,
          7,
          9,
          0,
          8,
          13,
          38,
          36,
          44,
          36,
          29,
          41,
          61,
          70,
          56,
          140,
          71,
          679,
          52,
          132,
          49,
          21
        ],
        [
          34,
          31,
          19,
          13,
          10,
          7,
          0,
          19,
          43,
          41,
          49,
          41,
          21,
          46,
          67,
          75,
          61,
          145,
          76,
          685,
          57,
          137,
          54,
          26
        ],
        [
          26,
          23,
          10,
          20,
          22,
          13,
          15,
          0,
          26,
          21,
          41,
          24,
          31,
          32,
          52,
          62,
          48,
          131,
          63,
          671,
          58,
          123,
          40,
          16
        ],
        [
          37,
          33,
          35,
          45,
          44,
          38,
          39,
          26,
          0,
          9,
          21,
          8,
          55,
          28,
          38,
          67,
          52,
          135,
          67,
          675,
          68,
          103,
          16,
          19
        ],
        [
          28,
          25,
          16,
          33,
          45,
          36,
          41,
          21,
          9,
          0,
          21,
          16,
          60,
          38,
          48,
          66,
          51,
          135,
          67,
          675,
          60,
          109,
          26,
          10
        ],
        [
          36,
          33,
          36,
          41,
          53,
          44,
          49,
          41,
          21,
          21,
          0,
          31,
          67,
          44,
          54,
          82,
          68,
          152,
          83,
          691,
          49,
          89,
          32,
          26
        ],
        [
          42,
          38,
          33,
          43,
          42,
          36,
          37,
          24,
          8,
          16,
          30,
          0,
          52,
          22,
          32,
          56,
          41,
          125,
          56,
          665,
          73,
          105,
          17,
          24
        ],
        [
          52,
          48,
          36,
          36,
          33,
          29,
          21,
          32,
          51,
          59,
          67,
          49,
          0,
          54,
          74,
          84,
          69,
          153,
          84,
          693,
          84,
          152,
          61,
          44
        ],
        [
          62,
          58,
          46,
          48,
          47,
          41,
          42,
          32,
          28,
          38,
          45,
          22,
          54,
          0,
          19,
          40,
          26,
          109,
          41,
          649,
          94,
          99,
          19,
          54
        ],
        [
          82,
          79,
          66,
          68,
          67,
          61,
          62,
          52,
          38,
          48,
          55,
          32,
          74,
          21,
          0,
          56,
          41,
          125,
          57,
          665,
          114,
          90,
          26,
          74
        ],
        [
          91,
          87,
          75,
          77,
          76,
          70,
          71,
          61,
          71,
          67,
          106,
          56,
          83,
          41,
          56,
          0,
          15,
          103,
          38,
          643,
          123,
          93,
          63,
          83
        ],
        [
          77,
          73,
          61,
          63,
          62,
          56,
          57,
          47,
          57,
          52,
          92,
          42,
          69,
          27,
          42,
          15,
          0,
          101,
          32,
          641,
          109,
          96,
          48,
          69
        ],
        [
          185,
          182,
          169,
          171,
          170,
          164,
          165,
          156,
          165,
          160,
          200,
          150,
          177,
          135,
          150,
          128,
          126,
          0,
          123,
          605,
          217,
          223,
          157,
          177
        ],
        [
          92,
          88,
          76,
          78,
          77,
          71,
          72,
          62,
          72,
          67,
          107,
          56,
          84,
          41,
          57,
          38,
          32,
          99,
          0,
          638,
          123,
          129,
          63,
          84
        ],
        [
          700,
          697,
          685,
          686,
          685,
          679,
          681,
          671,
          680,
          675,
          715,
          665,
          692,
          650,
          665,
          643,
          641,
          643,
          639,
          0,
          732,
          738,
          672,
          692
        ],
        [
          32,
          36,
          53,
          45,
          54,
          52,
          57,
          58,
          69,
          59,
          49,
          74,
          85,
          93,
          114,
          123,
          109,
          193,
          124,
          733,
          0,
          112,
          101,
          50
        ],
        [
          124,
          121,
          124,
          129,
          141,
          133,
          138,
          123,
          103,
          109,
          90,
          106,
          156,
          99,
          90,
          93,
          96,
          198,
          129,
          738,
          113,
          0,
          108,
          114
        ],
        [
          73,
          69,
          57,
          58,
          58,
          51,
          53,
          33,
          16,
          26,
          33,
          17,
          65,
          19,
          26,
          57,
          43,
          127,
          58,
          667,
          103,
          108,
          0,
          34
        ],
        [
          19,
          15,
          10,
          20,
          30,
          21,
          26,
          16,
          19,
          10,
          26,
          24,
          45,
          54,
          74,
          83,
          69,
          153,
          84,
          693,
          51,
          114,
          34,
          0
        ]
      ]
    },
    "pointe_soir": {
      "label": "Hyper-pointe soir (16h–20h)",
      "hours": "16h00 – 20h00",
      "coeff": 0.25,
      "speedRange": "8–10 km/h",
      "traffic": "Hyper-congestion",
      "durations": [
        [
          0,
          7,
          30,
          37,
          54,
          42,
          48,
          37,
          52,
          39,
          50,
          59,
          74,
          87,
          115,
          128,
          108,
          225,
          129,
          981,
          44,
          173,
          97,
          26
        ],
        [
          7,
          0,
          24,
          32,
          48,
          37,
          43,
          32,
          47,
          34,
          45,
          54,
          69,
          82,
          110,
          124,
          103,
          220,
          124,
          976,
          50,
          168,
          92,
          22
        ],
        [
          30,
          24,
          0,
          16,
          30,
          18,
          25,
          14,
          49,
          23,
          50,
          45,
          50,
          64,
          92,
          105,
          85,
          202,
          106,
          958,
          74,
          174,
          74,
          14
        ],
        [
          34,
          28,
          17,
          0,
          20,
          12,
          19,
          26,
          64,
          43,
          54,
          61,
          51,
          68,
          96,
          109,
          90,
          206,
          110,
          962,
          64,
          177,
          79,
          31
        ],
        [
          53,
          48,
          30,
          20,
          0,
          13,
          14,
          31,
          65,
          62,
          73,
          62,
          47,
          69,
          97,
          110,
          91,
          207,
          112,
          963,
          76,
          196,
          80,
          42
        ],
        [
          41,
          36,
          18,
          10,
          13,
          0,
          11,
          19,
          54,
          50,
          62,
          50,
          40,
          57,
          85,
          98,
          79,
          196,
          100,
          951,
          73,
          185,
          68,
          30
        ],
        [
          48,
          43,
          26,
          18,
          14,
          10,
          0,
          26,
          61,
          58,
          69,
          57,
          30,
          65,
          93,
          106,
          86,
          203,
          107,
          959,
          80,
          192,
          75,
          37
        ],
        [
          37,
          32,
          14,
          28,
          31,
          19,
          21,
          0,
          36,
          30,
          58,
          33,
          43,
          45,
          73,
          86,
          67,
          184,
          88,
          939,
          81,
          172,
          56,
          22
        ],
        [
          52,
          47,
          49,
          62,
          62,
          53,
          55,
          36,
          0,
          13,
          30,
          12,
          76,
          40,
          54,
          93,
          73,
          190,
          94,
          946,
          96,
          144,
          23,
          26
        ],
        [
          39,
          34,
          23,
          46,
          62,
          50,
          58,
          30,
          13,
          0,
          30,
          23,
          84,
          54,
          67,
          92,
          72,
          189,
          93,
          945,
          84,
          152,
          37,
          14
        ],
        [
          50,
          46,
          50,
          57,
          74,
          62,
          69,
          58,
          30,
          30,
          0,
          43,
          94,
          62,
          76,
          115,
          96,
          212,
          116,
          968,
          68,
          124,
          45,
          36
        ],
        [
          59,
          54,
          46,
          60,
          58,
          50,
          52,
          33,
          12,
          23,
          42,
          0,
          73,
          31,
          45,
          78,
          58,
          175,
          79,
          931,
          103,
          147,
          24,
          34
        ],
        [
          73,
          67,
          50,
          50,
          46,
          40,
          30,
          44,
          72,
          82,
          94,
          68,
          0,
          76,
          104,
          117,
          97,
          214,
          118,
          970,
          117,
          213,
          86,
          61
        ],
        [
          87,
          82,
          64,
          67,
          66,
          57,
          59,
          45,
          39,
          53,
          62,
          31,
          76,
          0,
          27,
          56,
          37,
          153,
          58,
          909,
          132,
          139,
          27,
          76
        ],
        [
          115,
          110,
          92,
          95,
          94,
          85,
          87,
          73,
          53,
          67,
          76,
          45,
          104,
          30,
          0,
          78,
          58,
          175,
          79,
          931,
          159,
          126,
          36,
          104
        ],
        [
          128,
          122,
          105,
          108,
          107,
          98,
          100,
          86,
          100,
          93,
          149,
          78,
          116,
          57,
          79,
          0,
          22,
          144,
          54,
          900,
          172,
          130,
          88,
          116
        ],
        [
          108,
          103,
          85,
          88,
          86,
          78,
          80,
          66,
          79,
          73,
          128,
          58,
          97,
          37,
          58,
          22,
          0,
          141,
          45,
          897,
          152,
          134,
          67,
          96
        ],
        [
          259,
          254,
          237,
          240,
          238,
          230,
          232,
          218,
          231,
          224,
          280,
          210,
          248,
          188,
          210,
          179,
          176,
          0,
          173,
          847,
          304,
          312,
          219,
          248
        ],
        [
          128,
          124,
          106,
          109,
          108,
          99,
          101,
          87,
          100,
          94,
          150,
          79,
          117,
          58,
          79,
          54,
          45,
          138,
          0,
          894,
          173,
          181,
          88,
          117
        ],
        [
          980,
          976,
          958,
          961,
          960,
          951,
          953,
          939,
          952,
          946,
          1002,
          931,
          969,
          910,
          931,
          900,
          897,
          900,
          894,
          0,
          1025,
          1033,
          940,
          969
        ],
        [
          45,
          50,
          74,
          64,
          75,
          73,
          80,
          81,
          96,
          83,
          68,
          103,
          118,
          131,
          160,
          172,
          152,
          270,
          174,
          1026,
          0,
          157,
          142,
          70
        ],
        [
          174,
          169,
          174,
          181,
          198,
          186,
          193,
          172,
          144,
          153,
          126,
          148,
          218,
          139,
          126,
          130,
          134,
          277,
          181,
          1033,
          158,
          0,
          151,
          160
        ],
        [
          102,
          97,
          79,
          82,
          81,
          72,
          74,
          47,
          23,
          37,
          46,
          24,
          91,
          27,
          36,
          80,
          60,
          177,
          81,
          933,
          144,
          151,
          0,
          48
        ],
        [
          26,
          22,
          14,
          28,
          42,
          30,
          37,
          22,
          26,
          14,
          36,
          33,
          62,
          75,
          104,
          116,
          97,
          214,
          118,
          970,
          71,
          159,
          48,
          0
        ]
      ]
    },
    "soiree": {
      "label": "Soirée (20h–00h)",
      "hours": "20h00 – 00h00",
      "coeff": 0.6,
      "speedRange": "18–24 km/h",
      "traffic": "Ralentissement",
      "durations": [
        [
          0,
          3,
          12,
          15,
          22,
          17,
          20,
          15,
          22,
          16,
          21,
          25,
          31,
          36,
          48,
          54,
          45,
          94,
          54,
          409,
          19,
          72,
          41,
          11
        ],
        [
          3,
          0,
          10,
          13,
          20,
          15,
          18,
          13,
          20,
          14,
          19,
          23,
          29,
          34,
          46,
          52,
          43,
          92,
          52,
          407,
          21,
          70,
          39,
          9
        ],
        [
          12,
          10,
          0,
          7,
          13,
          8,
          11,
          6,
          20,
          10,
          21,
          19,
          21,
          27,
          38,
          44,
          35,
          84,
          44,
          399,
          31,
          72,
          31,
          6
        ],
        [
          14,
          12,
          7,
          0,
          9,
          5,
          8,
          11,
          27,
          18,
          23,
          25,
          21,
          28,
          40,
          46,
          37,
          86,
          46,
          401,
          27,
          74,
          33,
          13
        ],
        [
          22,
          20,
          13,
          8,
          0,
          5,
          6,
          13,
          27,
          26,
          31,
          26,
          20,
          29,
          41,
          46,
          38,
          86,
          47,
          401,
          32,
          82,
          33,
          17
        ],
        [
          17,
          15,
          8,
          4,
          5,
          0,
          5,
          8,
          22,
          21,
          26,
          21,
          17,
          24,
          36,
          41,
          33,
          82,
          42,
          396,
          30,
          77,
          28,
          12
        ],
        [
          20,
          18,
          11,
          7,
          6,
          4,
          0,
          11,
          25,
          24,
          29,
          24,
          13,
          27,
          39,
          44,
          36,
          85,
          45,
          400,
          33,
          80,
          31,
          15
        ],
        [
          15,
          13,
          6,
          12,
          13,
          8,
          9,
          0,
          15,
          13,
          24,
          14,
          18,
          19,
          31,
          36,
          28,
          77,
          37,
          391,
          34,
          72,
          23,
          9
        ],
        [
          22,
          20,
          20,
          26,
          26,
          22,
          23,
          15,
          0,
          5,
          12,
          5,
          32,
          17,
          22,
          39,
          30,
          79,
          39,
          394,
          40,
          60,
          10,
          11
        ],
        [
          16,
          14,
          10,
          19,
          26,
          21,
          24,
          13,
          5,
          0,
          12,
          10,
          35,
          22,
          28,
          38,
          30,
          79,
          39,
          394,
          35,
          64,
          15,
          6
        ],
        [
          21,
          19,
          21,
          24,
          31,
          26,
          29,
          24,
          12,
          12,
          0,
          18,
          39,
          26,
          32,
          48,
          40,
          89,
          49,
          403,
          28,
          52,
          19,
          15
        ],
        [
          25,
          22,
          19,
          25,
          24,
          21,
          22,
          14,
          5,
          10,
          18,
          0,
          31,
          13,
          19,
          33,
          24,
          73,
          33,
          388,
          43,
          61,
          10,
          14
        ],
        [
          30,
          28,
          21,
          21,
          19,
          17,
          12,
          19,
          30,
          34,
          39,
          29,
          0,
          32,
          43,
          49,
          40,
          89,
          49,
          404,
          49,
          89,
          36,
          26
        ],
        [
          36,
          34,
          27,
          28,
          28,
          24,
          25,
          19,
          16,
          22,
          26,
          13,
          32,
          0,
          11,
          24,
          15,
          64,
          24,
          379,
          55,
          58,
          11,
          32
        ],
        [
          48,
          46,
          39,
          40,
          39,
          36,
          36,
          31,
          22,
          28,
          32,
          19,
          43,
          12,
          0,
          33,
          24,
          73,
          33,
          388,
          66,
          53,
          15,
          43
        ],
        [
          53,
          51,
          44,
          45,
          45,
          41,
          42,
          36,
          42,
          39,
          62,
          33,
          49,
          24,
          33,
          0,
          9,
          60,
          22,
          375,
          72,
          54,
          37,
          49
        ],
        [
          45,
          43,
          36,
          37,
          36,
          33,
          33,
          28,
          33,
          31,
          54,
          24,
          40,
          16,
          24,
          9,
          0,
          59,
          19,
          374,
          63,
          56,
          28,
          40
        ],
        [
          108,
          106,
          99,
          100,
          99,
          96,
          97,
          91,
          96,
          94,
          117,
          87,
          103,
          79,
          88,
          75,
          73,
          0,
          72,
          353,
          127,
          130,
          91,
          103
        ],
        [
          54,
          52,
          44,
          45,
          45,
          41,
          42,
          36,
          42,
          39,
          62,
          33,
          49,
          24,
          33,
          22,
          19,
          58,
          0,
          372,
          72,
          75,
          37,
          49
        ],
        [
          409,
          407,
          399,
          400,
          400,
          396,
          397,
          391,
          397,
          394,
          417,
          388,
          404,
          379,
          388,
          375,
          374,
          375,
          373,
          0,
          427,
          430,
          392,
          404
        ],
        [
          19,
          21,
          31,
          27,
          31,
          30,
          33,
          34,
          40,
          35,
          29,
          43,
          49,
          55,
          67,
          72,
          64,
          112,
          72,
          427,
          0,
          66,
          59,
          29
        ],
        [
          73,
          71,
          73,
          76,
          82,
          77,
          80,
          72,
          60,
          64,
          52,
          62,
          91,
          58,
          53,
          54,
          56,
          115,
          75,
          430,
          66,
          0,
          63,
          67
        ],
        [
          43,
          40,
          33,
          34,
          34,
          30,
          31,
          20,
          10,
          15,
          19,
          10,
          38,
          11,
          15,
          34,
          25,
          74,
          34,
          389,
          60,
          63,
          0,
          20
        ],
        [
          11,
          9,
          6,
          12,
          17,
          12,
          15,
          9,
          11,
          6,
          15,
          14,
          26,
          31,
          43,
          49,
          40,
          89,
          49,
          404,
          30,
          66,
          20,
          0
        ]
      ]
    }
  }
}